Workbook

Sheet CFO Guide
A1: CFO AI ROI Decision Model
C2: More Guides here ↓
A3: Use this workbook to decide whether an FP&A process should stay manual, use a Custom GPT, use coding automation, or justify an AI agent.
A5: How to use this template?
A7: 1 | B7: Edit blue/yellow input cells in the Assumptions sheet.
A8: 2 | B8: Review Calculations for NPV, ROI, payback, AI score, and token break-even price.
A9: 3 | B9: Use Dashboard to see the best option by FP&A process.
A11: Extra Tips
A12: A | B12: Use Token Breakeven to understand whether cheaper tokens could make agents viable later.
A13: B | B13: Keep human review for any process that touches financial outputs, even if an agent is profitable.
A14: C | B14: Upgrade from Custom GPT/Gemini Gem/Claude Skill to Agent only when incremental automation justifies incremental cost and control burden.
A16: Do not pay agent prices for Custom GPT problems. Token prices may fall, but accountability will not.

Sheet Reasoning
B2: Explanation of the Model
B3: AI should be treated like an investment decision, not a technology trend. A CFO should not ask, “Can AI do this?” The better question is, “Does AI save more money than it costs, after setup, training, review, risk, and maintenance?”
B5: The main formula is the decision rule. It says the value of AI is equal to the future labor savings from automation, minus the costs required to make AI work. Those costs include setup cost, learning cost, AI/token/tool cost, human review cost, and risk cost. In simple words: use AI only when the financial benefit is greater than the full cost of using it.
B7: The second rule is about payback. Even if AI creates value, it still needs to pay back fast enough. If it takes 12 months to build and learn the AI workflow, but the FP&A process will change in 6 months, then it is probably not worth it. The process may change before the company gets the benefit.
B9: A practical example would be monthly variance commentary. Today, an FP&A analyst may spend 10 hours every month pulling numbers, explaining variances, writing commentary, and preparing notes for the CFO. A cheap Custom GPT could be built using the company’s standard variance commentary format, examples of prior months, business definitions, and instructions such as: “Explain revenue variance by volume, price, mix, FX, and timing. Keep tone CFO-ready. Flag unusual movements.” That Custom GPT might do 70–80% of the drafting work.
B11: But the human still matters. The analyst or FP&A manager should review the numbers, check whether the explanation makes business sense, add judgment, remove weak wording, and make sure nothing is misleading. In that setup, the AI does the repetitive first draft, and the human provides judgment, accountability, and context. This is usually cheap, fast to implement, and easy to control.
B13: Now compare that to a fully autonomous AI agent. The agent might connect to Excel, ERP exports, planning systems, Slack, email, and maybe a data warehouse. It may pull data, clean it, run analysis, write the commentary, create slides, send alerts, and update files automatically. That sounds powerful, but it can become expensive quickly. You may need API costs, orchestration tools, monitoring, security reviews, permissions, testing, error handling, audit logs, and someone to maintain it every time the forecast model, chart of accounts, business structure, or reporting calendar changes.
B15: So even if the AI agent automates 90–95% of the work, it may still be worse financially. The Custom GPT might save 7 hours per month with almost no technical maintenance. The agent might save 9 hours per month but cost thousands of dollars to build and maintain. The extra 2 hours saved may not justify the extra complexity.

Sheet 1. Assumptions
A1: Assumptions Input — Edit blue/yellow cells
A2: All sample values are illustrative. Replace with your company salary rates, process time, token usage, tool costs, and review/risk assumptions.
A4: Process ID | B4: Process Name | C4: AI Option | D4: Option Rank | E4: Salary ($/hr) | F4: Current Hours / Run | G4: Frequency / Month | H4: Process Life (Months) | I4: Automation Rate | J4: Quality Factor | K4: Setup Hours | L4: Learning Hours / User | M4: Users | N4: Input Tokens / Run (M) | O4: Output Tokens / Run (M) | P4: Input Token Price ($/1M) | Q4: Output Token Price ($/1M) | R4: Fixed Tool Cost / Month | S4: Review Hours / Run | T4: Error Probability | U4: Error Impact ($) | V4: Control Strength | W4: Annual Discount Rate | X4: Maintenance Hours / Month | Y4: Integration / Governance Cost ($) | Z4: Source / Note
A5: 1 | B5: Monthly Variance Analysis | C5: Manual AI | D5: 2 | E5: 100 | F5: 10 | G5: 1 | H5: 18 | I5: 0.45 | J5: 0.85 | K5: 1 | L5: 1 | M5: 2 | N5: 0.02 | O5: 0.01 | P5: 3 | Q5: 15 | R5: 20 | S5: 4 | T5: 0.03 | U5: 2000 | V5: 0.65 | W5: 0.1 | X5: 0.5 | Y5: 0 | Z5: Illustrative CFO assumption. Replace with actual FP&A data.
A6: 1 | B6: Monthly Variance Analysis | C6: Custom GPT | D6: 3 | E6: 100 | F6: 10 | G6: 1 | H6: 18 | I6: 0.75 | J6: 0.9 | K6: 8 | L6: 2 | M6: 3 | N6: 0.05 | O6: 0.025 | P6: 3 | Q6: 15 | R6: 50 | S6: 2.5 | T6: 0.03 | U6: 2000 | V6: 0.75 | W6: 0.1 | X6: 1 | Y6: 0 | Z6: Illustrative. Custom GPT with human review.
A7: 1 | B7: Monthly Variance Analysis | C7: AI Agent | D7: 5 | E7: 100 | F7: 10 | G7: 1 | H7: 18 | I7: 0.95 | J7: 0.88 | K7: 80 | L7: 6 | M7: 3 | N7: 0.3 | O7: 0.15 | P7: 3 | Q7: 15 | R7: 900 | S7: 1.5 | T7: 0.04 | U7: 5000 | V7: 0.8 | W7: 0.1 | X7: 8 | Y7: 5000 | Z7: Illustrative. Agent includes monitoring, governance, and integration cost.
A8: 2 | B8: Board Deck Commentary | C8: Manual AI | D8: 2 | E8: 120 | F8: 8 | G8: 1 | H8: 12 | I8: 0.45 | J8: 0.8 | K8: 1 | L8: 1 | M8: 2 | N8: 0.03 | O8: 0.02 | P8: 3 | Q8: 15 | R8: 20 | S8: 4 | T8: 0.05 | U8: 3000 | V8: 0.75 | W8: 0.1 | X8: 0.5 | Y8: 0 | Z8: Illustrative. High review due to board-level output.
A9: 2 | B9: Board Deck Commentary | C9: Custom GPT | D9: 3 | E9: 120 | F9: 8 | G9: 1 | H9: 12 | I9: 0.65 | J9: 0.86 | K9: 6 | L9: 2 | M9: 3 | N9: 0.06 | O9: 0.04 | P9: 3 | Q9: 15 | R9: 50 | S9: 3 | T9: 0.05 | U9: 3000 | V9: 0.8 | W9: 0.1 | X9: 1 | Y9: 0 | Z9: Illustrative. Trained on company tone and prior commentary.
A10: 2 | B10: Board Deck Commentary | C10: AI Agent | D10: 5 | E10: 120 | F10: 8 | G10: 1 | H10: 12 | I10: 0.9 | J10: 0.82 | K10: 70 | L10: 5 | M10: 3 | N10: 0.25 | O10: 0.2 | P10: 3 | Q10: 15 | R10: 1000 | S10: 2 | T10: 0.06 | U10: 6000 | V10: 0.85 | W10: 0.1 | X10: 6 | Y10: 4000 | Z10: Illustrative. Agent may be overbuilt for deck commentary.
A11: 3 | B11: Forecast Model Refresh | C11: Coding Copilot | D11: 4 | E11: 110 | F11: 16 | G11: 2 | H11: 24 | I11: 0.7 | J11: 0.9 | K11: 20 | L11: 3 | M11: 2 | N11: 0.08 | O11: 0.03 | P11: 3 | Q11: 15 | R11: 100 | S11: 3 | T11: 0.04 | U11: 4000 | V11: 0.8 | W11: 0.1 | X11: 2 | Y11: 500 | Z11: Illustrative. Repeatable Python/Excel automation.
A12: 3 | B12: Forecast Model Refresh | C12: AI Agent | D12: 5 | E12: 110 | F12: 16 | G12: 2 | H12: 24 | I12: 0.92 | J12: 0.88 | K12: 100 | L12: 8 | M12: 2 | N12: 0.6 | O12: 0.25 | P12: 3 | Q12: 15 | R12: 1500 | S12: 2 | T12: 0.05 | U12: 8000 | V12: 0.85 | W12: 0.1 | X12: 10 | Y12: 7000 | Z12: Illustrative. Agent for multi-step recurring workflow.
A13: 4 | B13: Ad Hoc Business Case | C13: Manual AI | D13: 2 | E13: 130 | F13: 6 | G13: 0.5 | H13: 6 | I13: 0.5 | J13: 0.82 | K13: 1 | L13: 0.5 | M13: 1 | N13: 0.02 | O13: 0.015 | P13: 3 | Q13: 15 | R13: 20 | S13: 2.5 | T13: 0.03 | U13: 1500 | V13: 0.7 | W13: 0.1 | X13: 0.2 | Y13: 0 | Z13: Illustrative. Low frequency favors light AI only.
A14: 4 | B14: Ad Hoc Business Case | C14: Custom GPT | D14: 3 | E14: 130 | F14: 6 | G14: 0.5 | H14: 6 | I14: 0.7 | J14: 0.85 | K14: 8 | L14: 2 | M14: 2 | N14: 0.05 | O14: 0.03 | P14: 3 | Q14: 15 | R14: 50 | S14: 2 | T14: 0.03 | U14: 1500 | V14: 0.75 | W14: 0.1 | X14: 0.8 | Y14: 0 | Z14: Illustrative. May be too much setup for low frequency.
A15: 5 | B15: ERP Forecast Upload | C15: Coding Copilot | D15: 4 | E15: 105 | F15: 12 | G15: 1 | H15: 18 | I15: 0.65 | J15: 0.9 | K15: 24 | L15: 3 | M15: 2 | N15: 0.1 | O15: 0.03 | P15: 3 | Q15: 15 | R15: 150 | S15: 3 | T15: 0.06 | U15: 10000 | V15: 0.85 | W15: 0.1 | X15: 2 | Y15: 1000 | Z15: Illustrative. Controlled script may beat agent for risk.
A16: 5 | B16: ERP Forecast Upload | C16: AI Agent | D16: 5 | E16: 105 | F16: 12 | G16: 1 | H16: 18 | I16: 0.93 | J16: 0.86 | K16: 120 | L16: 8 | M16: 2 | N16: 0.8 | O16: 0.3 | P16: 3 | Q16: 15 | R16: 1800 | S16: 2 | T16: 0.08 | U16: 20000 | V16: 0.9 | W16: 0.1 | X16: 12 | Y16: 10000 | Z16: Illustrative. Agent requires strong controls and audit trail.

Sheet 2. Calculations
A1: Calculations — Formula-driven AI ROI by option
A2: Black cells are formulas. This sheet calculates the CFO decision equation, payback, AI score, and break-even token price.
A4: Process Name | B4: AI Option | C4: Option Rank | D4: Monthly Discount Rate | E4: Baseline Monthly Cost | F4: Effective Automation Rate | G4: Gross Monthly Labor Savings | H4: Monthly Token Cost | I4: Monthly Tool Cost | J4: Monthly Review Cost | K4: Monthly Risk Cost | L4: Monthly Maintenance Cost | M4: Total Monthly AI Cost | N4: Monthly Net Savings | O4: Setup Cost | P4: Learning Cost | Q4: Upfront Cost | R4: Expected Process Life | S4: PV Factor | T4: PV Net Savings | U4: NPV | V4: ROI | W4: Payback Months | X4: AI Score | Y4: PV Tokens Used (M) | Z4: Actual Blended Token Price ($/1M) | AA4: Max Break-even Token Price ($/1M) | AB4: Recommendation | AC4: CFO Explanation
A5: ='1. Assumptions'!B5 -> Monthly Variance Analysis | B5: ='1. Assumptions'!C5 -> Manual AI | C5: ='1. Assumptions'!D5 -> 2 | D5: =(1+'1. Assumptions'!W5)^(1/12)-1 -> 0.0079741404 | E5: ='1. Assumptions'!E5*'1. Assumptions'!F5*'1. Assumptions'!G5 -> 1000 | F5: ='1. Assumptions'!I5*'1. Assumptions'!J5 -> 0.3825 | G5: ='1. Assumptions'!E5*'1. Assumptions'!F5*'1. Assumptions'!G5*F5 -> 382.5 | H5: =('1. Assumptions'!N5*'1. Assumptions'!P5+'1. Assumptions'!O5*'1. Assumptions'!Q5)*'1. Assumptions'!G5 -> 0.21 | I5: ='1. Assumptions'!R5 -> 20 | J5: ='1. Assumptions'!S5*'1. Assumptions'!E5*'1. Assumptions'!G5 -> 400 | K5: ='1. Assumptions'!T5*'1. Assumptions'!U5*(1-'1. Assumptions'!V5)*'1. Assumptions'!G5 -> 21 | L5: ='1. Assumptions'!X5*'1. Assumptions'!E5 -> 50 | M5: =H5+I5+J5+K5+L5 -> 491.21 | N5: =G5-M5 -> -108.71 | O5: ='1. Assumptions'!K5*'1. Assumptions'!E5+'1. Assumptions'!Y5 -> 100 | P5: ='1. Assumptions'!L5*'1. Assumptions'!M5*'1. Assumptions'!E5 -> 200 | Q5: =O5+P5 -> 300 | R5: ='1. Assumptions'!H5 -> 18 | S5: =IF(D5=0,R5,(1-(1+D5)^(-R5))/D5) -> 16.70598 | T5: =N5*S5 -> -1816.1071 | U5: =T5-Q5 -> -2116.1071 | V5: =IF(Q5=0,"",(N5*R5-Q5)/Q5) -> -7.5226 | W5: =IF(N5>0,Q5/N5,"") | X5: =IF((Q5+M5*R5)>0,(G5*R5)/(Q5+M5*R5),"") -> 0.7531356 | Y5: =('1. Assumptions'!N5+'1. Assumptions'!O5)*'1. Assumptions'!G5*S5 -> 0.50117939 | Z5: =IF(('1. Assumptions'!N5+'1. Assumptions'!O5)*'1. Assumptions'!G5>0,H5/(('1. Assumptions'!N5+'1. Assumptions'!O5)*'1. Assumptions'!G5),"") -> 7 | AA5: =IF(Y5>0,((G5-I5-J5-K5-L5)*S5-Q5)/Y5,"") -> -4215.2547 | AB5: =IF(OR(U5<=0,N5<=0),"Do not automate",IF(W5>R5,"Do not automate - payback exceeds process life",IF(ISNUMBER(SEARCH("AI Agent",B5)),"Consider AI agent with controls",IF(ISNUMBER(SEARCH("Coding",B5)),"Use coding copilot / structured automation",IF(ISNUMBER(SEARCH("Custom GPT",B5)),"Use Custom GPT / prompt workflow","Use manual AI / light AI"))))) -> Do not automate | AC5: =IF(U5<=0,"Negative NPV: costs, review, risk, or setup exceed discounted savings.",IF(W5>R5,"Payback exceeds expected process life; wait until process stabilizes or reduce setup cost.",IF(ISNUMBER(SEARCH("AI Agent",B5)),"Agent may be justified, but only with controls, monitoring, and human approval.",IF(ISNUMBER(SEARCH("Custom GPT",B5)),"Custom GPT likely captures most value without full agent cost.","Positive NPV: use the recommended level and maintain human review.")))) -> Negative NPV: costs, review, risk, or setup exceed discounted savings.
A6: ='1. Assumptions'!B6 -> Monthly Variance Analysis | B6: ='1. Assumptions'!C6 -> Custom GPT | C6: ='1. Assumptions'!D6 -> 3 | D6: =(1+'1. Assumptions'!W6)^(1/12)-1 -> 0.0079741404 | E6: ='1. Assumptions'!E6*'1. Assumptions'!F6*'1. Assumptions'!G6 -> 1000 | F6: ='1. Assumptions'!I6*'1. Assumptions'!J6 -> 0.675 | G6: ='1. Assumptions'!E6*'1. Assumptions'!F6*'1. Assumptions'!G6*F6 -> 675 | H6: =('1. Assumptions'!N6*'1. Assumptions'!P6+'1. Assumptions'!O6*'1. Assumptions'!Q6)*'1. Assumptions'!G6 -> 0.525 | I6: ='1. Assumptions'!R6 -> 50 | J6: ='1. Assumptions'!S6*'1. Assumptions'!E6*'1. Assumptions'!G6 -> 250 | K6: ='1. Assumptions'!T6*'1. Assumptions'!U6*(1-'1. Assumptions'!V6)*'1. Assumptions'!G6 -> 15 | L6: ='1. Assumptions'!X6*'1. Assumptions'!E6 -> 100 | M6: =H6+I6+J6+K6+L6 -> 415.525 | N6: =G6-M6 -> 259.475 | O6: ='1. Assumptions'!K6*'1. Assumptions'!E6+'1. Assumptions'!Y6 -> 800 | P6: ='1. Assumptions'!L6*'1. Assumptions'!M6*'1. Assumptions'!E6 -> 600 | Q6: =O6+P6 -> 1400 | R6: ='1. Assumptions'!H6 -> 18 | S6: =IF(D6=0,R6,(1-(1+D6)^(-R6))/D6) -> 16.70598 | T6: =N6*S6 -> 4334.7841 | U6: =T6-Q6 -> 2934.7841 | V6: =IF(Q6=0,"",(N6*R6-Q6)/Q6) -> 2.3361071 | W6: =IF(N6>0,Q6/N6,"") -> 5.3955102 | X6: =IF((Q6+M6*R6)>0,(G6*R6)/(Q6+M6*R6),"") -> 1.368328 | Y6: =('1. Assumptions'!N6+'1. Assumptions'!O6)*'1. Assumptions'!G6*S6 -> 1.2529485 | Z6: =IF(('1. Assumptions'!N6+'1. Assumptions'!O6)*'1. Assumptions'!G6>0,H6/(('1. Assumptions'!N6+'1. Assumptions'!O6)*'1. Assumptions'!G6),"") -> 7 | AA6: =IF(Y6>0,((G6-I6-J6-K6-L6)*S6-Q6)/Y6,"") -> 2349.3023 | AB6: =IF(OR(U6<=0,N6<=0),"Do not automate",IF(W6>R6,"Do not automate - payback exceeds process life",IF(ISNUMBER(SEARCH("AI Agent",B6)),"Consider AI agent with controls",IF(ISNUMBER(SEARCH("Coding",B6)),"Use coding copilot / structured automation",IF(ISNUMBER(SEARCH("Custom GPT",B6)),"Use Custom GPT / prompt workflow","Use manual AI / light AI"))))) -> Use Custom GPT / prompt workflow | AC6: =IF(U6<=0,"Negative NPV: costs, review, risk, or setup exceed discounted savings.",IF(W6>R6,"Payback exceeds expected process life; wait until process stabilizes or reduce setup cost.",IF(ISNUMBER(SEARCH("AI Agent",B6)),"Agent may be justified, but only with controls, monitoring, and human approval.",IF(ISNUMBER(SEARCH("Custom GPT",B6)),"Custom GPT likely captures most value without full agent cost.","Positive NPV: use the recommended level and maintain human review.")))) -> Custom GPT likely captures most value without full agent cost.
A7: ='1. Assumptions'!B7 -> Monthly Variance Analysis | B7: ='1. Assumptions'!C7 -> AI Agent | C7: ='1. Assumptions'!D7 -> 5 | D7: =(1+'1. Assumptions'!W7)^(1/12)-1 -> 0.0079741404 | E7: ='1. Assumptions'!E7*'1. Assumptions'!F7*'1. Assumptions'!G7 -> 1000 | F7: ='1. Assumptions'!I7*'1. Assumptions'!J7 -> 0.836 | G7: ='1. Assumptions'!E7*'1. Assumptions'!F7*'1. Assumptions'!G7*F7 -> 836 | H7: =('1. Assumptions'!N7*'1. Assumptions'!P7+'1. Assumptions'!O7*'1. Assumptions'!Q7)*'1. Assumptions'!G7 -> 3.15 | I7: ='1. Assumptions'!R7 -> 900 | J7: ='1. Assumptions'!S7*'1. Assumptions'!E7*'1. Assumptions'!G7 -> 150 | K7: ='1. Assumptions'!T7*'1. Assumptions'!U7*(1-'1. Assumptions'!V7)*'1. Assumptions'!G7 -> 40 | L7: ='1. Assumptions'!X7*'1. Assumptions'!E7 -> 800 | M7: =H7+I7+J7+K7+L7 -> 1893.15 | N7: =G7-M7 -> -1057.15 | O7: ='1. Assumptions'!K7*'1. Assumptions'!E7+'1. Assumptions'!Y7 -> 13000 | P7: ='1. Assumptions'!L7*'1. Assumptions'!M7*'1. Assumptions'!E7 -> 1800 | Q7: =O7+P7 -> 14800 | R7: ='1. Assumptions'!H7 -> 18 | S7: =IF(D7=0,R7,(1-(1+D7)^(-R7))/D7) -> 16.70598 | T7: =N7*S7 -> -17660.726 | U7: =T7-Q7 -> -32460.726 | V7: =IF(Q7=0,"",(N7*R7-Q7)/Q7) -> -2.285723 | W7: =IF(N7>0,Q7/N7,"") | X7: =IF((Q7+M7*R7)>0,(G7*R7)/(Q7+M7*R7),"") -> 0.30787676 | Y7: =('1. Assumptions'!N7+'1. Assumptions'!O7)*'1. Assumptions'!G7*S7 -> 7.5176909 | Z7: =IF(('1. Assumptions'!N7+'1. Assumptions'!O7)*'1. Assumptions'!G7>0,H7/(('1. Assumptions'!N7+'1. Assumptions'!O7)*'1. Assumptions'!G7),"") -> 7 | AA7: =IF(Y7>0,((G7-I7-J7-K7-L7)*S7-Q7)/Y7,"") -> -4310.9118 | AB7: =IF(OR(U7<=0,N7<=0),"Do not automate",IF(W7>R7,"Do not automate - payback exceeds process life",IF(ISNUMBER(SEARCH("AI Agent",B7)),"Consider AI agent with controls",IF(ISNUMBER(SEARCH("Coding",B7)),"Use coding copilot / structured automation",IF(ISNUMBER(SEARCH("Custom GPT",B7)),"Use Custom GPT / prompt workflow","Use manual AI / light AI"))))) -> Do not automate | AC7: =IF(U7<=0,"Negative NPV: costs, review, risk, or setup exceed discounted savings.",IF(W7>R7,"Payback exceeds expected process life; wait until process stabilizes or reduce setup cost.",IF(ISNUMBER(SEARCH("AI Agent",B7)),"Agent may be justified, but only with controls, monitoring, and human approval.",IF(ISNUMBER(SEARCH("Custom GPT",B7)),"Custom GPT likely captures most value without full agent cost.","Positive NPV: use the recommended level and maintain human review.")))) -> Negative NPV: costs, review, risk, or setup exceed discounted savings.
A8: ='1. Assumptions'!B8 -> Board Deck Commentary | B8: ='1. Assumptions'!C8 -> Manual AI | C8: ='1. Assumptions'!D8 -> 2 | D8: =(1+'1. Assumptions'!W8)^(1/12)-1 -> 0.0079741404 | E8: ='1. Assumptions'!E8*'1. Assumptions'!F8*'1. Assumptions'!G8 -> 960 | F8: ='1. Assumptions'!I8*'1. Assumptions'!J8 -> 0.36 | G8: ='1. Assumptions'!E8*'1. Assumptions'!F8*'1. Assumptions'!G8*F8 -> 345.6 | H8: =('1. Assumptions'!N8*'1. Assumptions'!P8+'1. Assumptions'!O8*'1. Assumptions'!Q8)*'1. Assumptions'!G8 -> 0.39 | I8: ='1. Assumptions'!R8 -> 20 | J8: ='1. Assumptions'!S8*'1. Assumptions'!E8*'1. Assumptions'!G8 -> 480 | K8: ='1. Assumptions'!T8*'1. Assumptions'!U8*(1-'1. Assumptions'!V8)*'1. Assumptions'!G8 -> 37.5 | L8: ='1. Assumptions'!X8*'1. Assumptions'!E8 -> 60 | M8: =H8+I8+J8+K8+L8 -> 597.89 | N8: =G8-M8 -> -252.29 | O8: ='1. Assumptions'!K8*'1. Assumptions'!E8+'1. Assumptions'!Y8 -> 120 | P8: ='1. Assumptions'!L8*'1. Assumptions'!M8*'1. Assumptions'!E8 -> 240 | Q8: =O8+P8 -> 360 | R8: ='1. Assumptions'!H8 -> 12 | S8: =IF(D8=0,R8,(1-(1+D8)^(-R8))/D8) -> 11.400488 | T8: =N8*S8 -> -2876.2291 | U8: =T8-Q8 -> -3236.2291 | V8: =IF(Q8=0,"",(N8*R8-Q8)/Q8) -> -9.4096667 | W8: =IF(N8>0,Q8/N8,"") | X8: =IF((Q8+M8*R8)>0,(G8*R8)/(Q8+M8*R8),"") -> 0.55041488 | Y8: =('1. Assumptions'!N8+'1. Assumptions'!O8)*'1. Assumptions'!G8*S8 -> 0.57002439 | Z8: =IF(('1. Assumptions'!N8+'1. Assumptions'!O8)*'1. Assumptions'!G8>0,H8/(('1. Assumptions'!N8+'1. Assumptions'!O8)*'1. Assumptions'!G8),"") -> 7.8 | AA8: =IF(Y8>0,((G8-I8-J8-K8-L8)*S8-Q8)/Y8,"") -> -5669.5519 | AB8: =IF(OR(U8<=0,N8<=0),"Do not automate",IF(W8>R8,"Do not automate - payback exceeds process life",IF(ISNUMBER(SEARCH("AI Agent",B8)),"Consider AI agent with controls",IF(ISNUMBER(SEARCH("Coding",B8)),"Use coding copilot / structured automation",IF(ISNUMBER(SEARCH("Custom GPT",B8)),"Use Custom GPT / prompt workflow","Use manual AI / light AI"))))) -> Do not automate | AC8: =IF(U8<=0,"Negative NPV: costs, review, risk, or setup exceed discounted savings.",IF(W8>R8,"Payback exceeds expected process life; wait until process stabilizes or reduce setup cost.",IF(ISNUMBER(SEARCH("AI Agent",B8)),"Agent may be justified, but only with controls, monitoring, and human approval.",IF(ISNUMBER(SEARCH("Custom GPT",B8)),"Custom GPT likely captures most value without full agent cost.","Positive NPV: use the recommended level and maintain human review.")))) -> Negative NPV: costs, review, risk, or setup exceed discounted savings.
A9: ='1. Assumptions'!B9 -> Board Deck Commentary | B9: ='1. Assumptions'!C9 -> Custom GPT | C9: ='1. Assumptions'!D9 -> 3 | D9: =(1+'1. Assumptions'!W9)^(1/12)-1 -> 0.0079741404 | E9: ='1. Assumptions'!E9*'1. Assumptions'!F9*'1. Assumptions'!G9 -> 960 | F9: ='1. Assumptions'!I9*'1. Assumptions'!J9 -> 0.559 | G9: ='1. Assumptions'!E9*'1. Assumptions'!F9*'1. Assumptions'!G9*F9 -> 536.64 | H9: =('1. Assumptions'!N9*'1. Assumptions'!P9+'1. Assumptions'!O9*'1. Assumptions'!Q9)*'1. Assumptions'!G9 -> 0.78 | I9: ='1. Assumptions'!R9 -> 50 | J9: ='1. Assumptions'!S9*'1. Assumptions'!E9*'1. Assumptions'!G9 -> 360 | K9: ='1. Assumptions'!T9*'1. Assumptions'!U9*(1-'1. Assumptions'!V9)*'1. Assumptions'!G9 -> 30 | L9: ='1. Assumptions'!X9*'1. Assumptions'!E9 -> 120 | M9: =H9+I9+J9+K9+L9 -> 560.78 | N9: =G9-M9 -> -24.14 | O9: ='1. Assumptions'!K9*'1. Assumptions'!E9+'1. Assumptions'!Y9 -> 720 | P9: ='1. Assumptions'!L9*'1. Assumptions'!M9*'1. Assumptions'!E9 -> 720 | Q9: =O9+P9 -> 1440 | R9: ='1. Assumptions'!H9 -> 12 | S9: =IF(D9=0,R9,(1-(1+D9)^(-R9))/D9) -> 11.400488 | T9: =N9*S9 -> -275.20778 | U9: =T9-Q9 -> -1715.2078 | V9: =IF(Q9=0,"",(N9*R9-Q9)/Q9) -> -1.2011667 | W9: =IF(N9>0,Q9/N9,"") | X9: =IF((Q9+M9*R9)>0,(G9*R9)/(Q9+M9*R9),"") -> 0.78827228 | Y9: =('1. Assumptions'!N9+'1. Assumptions'!O9)*'1. Assumptions'!G9*S9 -> 1.1400488 | Z9: =IF(('1. Assumptions'!N9+'1. Assumptions'!O9)*'1. Assumptions'!G9>0,H9/(('1. Assumptions'!N9+'1. Assumptions'!O9)*'1. Assumptions'!G9),"") -> 7.8 | AA9: =IF(Y9>0,((G9-I9-J9-K9-L9)*S9-Q9)/Y9,"") -> -1496.7038 | AB9: =IF(OR(U9<=0,N9<=0),"Do not automate",IF(W9>R9,"Do not automate - payback exceeds process life",IF(ISNUMBER(SEARCH("AI Agent",B9)),"Consider AI agent with controls",IF(ISNUMBER(SEARCH("Coding",B9)),"Use coding copilot / structured automation",IF(ISNUMBER(SEARCH("Custom GPT",B9)),"Use Custom GPT / prompt workflow","Use manual AI / light AI"))))) -> Do not automate | AC9: =IF(U9<=0,"Negative NPV: costs, review, risk, or setup exceed discounted savings.",IF(W9>R9,"Payback exceeds expected process life; wait until process stabilizes or reduce setup cost.",IF(ISNUMBER(SEARCH("AI Agent",B9)),"Agent may be justified, but only with controls, monitoring, and human approval.",IF(ISNUMBER(SEARCH("Custom GPT",B9)),"Custom GPT likely captures most value without full agent cost.","Positive NPV: use the recommended level and maintain human review.")))) -> Negative NPV: costs, review, risk, or setup exceed discounted savings.
A10: ='1. Assumptions'!B10 -> Board Deck Commentary | B10: ='1. Assumptions'!C10 -> AI Agent | C10: ='1. Assumptions'!D10 -> 5 | D10: =(1+'1. Assumptions'!W10)^(1/12)-1 -> 0.0079741404 | E10: ='1. Assumptions'!E10*'1. Assumptions'!F10*'1. Assumptions'!G10 -> 960 | F10: ='1. Assumptions'!I10*'1. Assumptions'!J10 -> 0.738 | G10: ='1. Assumptions'!E10*'1. Assumptions'!F10*'1. Assumptions'!G10*F10 -> 708.48 | H10: =('1. Assumptions'!N10*'1. Assumptions'!P10+'1. Assumptions'!O10*'1. Assumptions'!Q10)*'1. Assumptions'!G10 -> 3.75 | I10: ='1. Assumptions'!R10 -> 1000 | J10: ='1. Assumptions'!S10*'1. Assumptions'!E10*'1. Assumptions'!G10 -> 240 | K10: ='1. Assumptions'!T10*'1. Assumptions'!U10*(1-'1. Assumptions'!V10)*'1. Assumptions'!G10 -> 54 | L10: ='1. Assumptions'!X10*'1. Assumptions'!E10 -> 720 | M10: =H10+I10+J10+K10+L10 -> 2017.75 | N10: =G10-M10 -> -1309.27 | O10: ='1. Assumptions'!K10*'1. Assumptions'!E10+'1. Assumptions'!Y10 -> 12400 | P10: ='1. Assumptions'!L10*'1. Assumptions'!M10*'1. Assumptions'!E10 -> 1800 | Q10: =O10+P10 -> 14200 | R10: ='1. Assumptions'!H10 -> 12 | S10: =IF(D10=0,R10,(1-(1+D10)^(-R10))/D10) -> 11.400488 | T10: =N10*S10 -> -14926.317 | U10: =T10-Q10 -> -29126.317 | V10: =IF(Q10=0,"",(N10*R10-Q10)/Q10) -> -2.1064254 | W10: =IF(N10>0,Q10/N10,"") | X10: =IF((Q10+M10*R10)>0,(G10*R10)/(Q10+M10*R10),"") -> 0.22132507 | Y10: =('1. Assumptions'!N10+'1. Assumptions'!O10)*'1. Assumptions'!G10*S10 -> 5.1302195 | Z10: =IF(('1. Assumptions'!N10+'1. Assumptions'!O10)*'1. Assumptions'!G10>0,H10/(('1. Assumptions'!N10+'1. Assumptions'!O10)*'1. Assumptions'!G10),"") -> 8.3333333 | AA10: =IF(Y10>0,((G10-I10-J10-K10-L10)*S10-Q10)/Y10,"") -> -5669.0683 | AB10: =IF(OR(U10<=0,N10<=0),"Do not automate",IF(W10>R10,"Do not automate - payback exceeds process life",IF(ISNUMBER(SEARCH("AI Agent",B10)),"Consider AI agent with controls",IF(ISNUMBER(SEARCH("Coding",B10)),"Use coding copilot / structured automation",IF(ISNUMBER(SEARCH("Custom GPT",B10)),"Use Custom GPT / prompt workflow","Use manual AI / light AI"))))) -> Do not automate | AC10: =IF(U10<=0,"Negative NPV: costs, review, risk, or setup exceed discounted savings.",IF(W10>R10,"Payback exceeds expected process life; wait until process stabilizes or reduce setup cost.",IF(ISNUMBER(SEARCH("AI Agent",B10)),"Agent may be justified, but only with controls, monitoring, and human approval.",IF(ISNUMBER(SEARCH("Custom GPT",B10)),"Custom GPT likely captures most value without full agent cost.","Positive NPV: use the recommended level and maintain human review.")))) -> Negative NPV: costs, review, risk, or setup exceed discounted savings.
A11: ='1. Assumptions'!B11 -> Forecast Model Refresh | B11: ='1. Assumptions'!C11 -> Coding Copilot | C11: ='1. Assumptions'!D11 -> 4 | D11: =(1+'1. Assumptions'!W11)^(1/12)-1 -> 0.0079741404 | E11: ='1. Assumptions'!E11*'1. Assumptions'!F11*'1. Assumptions'!G11 -> 3520 | F11: ='1. Assumptions'!I11*'1. Assumptions'!J11 -> 0.63 | G11: ='1. Assumptions'!E11*'1. Assumptions'!F11*'1. Assumptions'!G11*F11 -> 2217.6 | H11: =('1. Assumptions'!N11*'1. Assumptions'!P11+'1. Assumptions'!O11*'1. Assumptions'!Q11)*'1. Assumptions'!G11 -> 1.38 | I11: ='1. Assumptions'!R11 -> 100 | J11: ='1. Assumptions'!S11*'1. Assumptions'!E11*'1. Assumptions'!G11 -> 660 | K11: ='1. Assumptions'!T11*'1. Assumptions'!U11*(1-'1. Assumptions'!V11)*'1. Assumptions'!G11 -> 64 | L11: ='1. Assumptions'!X11*'1. Assumptions'!E11 -> 220 | M11: =H11+I11+J11+K11+L11 -> 1045.38 | N11: =G11-M11 -> 1172.22 | O11: ='1. Assumptions'!K11*'1. Assumptions'!E11+'1. Assumptions'!Y11 -> 2700 | P11: ='1. Assumptions'!L11*'1. Assumptions'!M11*'1. Assumptions'!E11 -> 660 | Q11: =O11+P11 -> 3360 | R11: ='1. Assumptions'!H11 -> 24 | S11: =IF(D11=0,R11,(1-(1+D11)^(-R11))/D11) -> 21.764568 | T11: =N11*S11 -> 25512.862 | U11: =T11-Q11 -> 22152.862 | V11: =IF(Q11=0,"",(N11*R11-Q11)/Q11) -> 7.373 | W11: =IF(N11>0,Q11/N11,"") -> 2.8663561 | X11: =IF((Q11+M11*R11)>0,(G11*R11)/(Q11+M11*R11),"") -> 1.8707925 | Y11: =('1. Assumptions'!N11+'1. Assumptions'!O11)*'1. Assumptions'!G11*S11 -> 4.7882049 | Z11: =IF(('1. Assumptions'!N11+'1. Assumptions'!O11)*'1. Assumptions'!G11>0,H11/(('1. Assumptions'!N11+'1. Assumptions'!O11)*'1. Assumptions'!G11),"") -> 6.2727273 | AA11: =IF(Y11>0,((G11-I11-J11-K11-L11)*S11-Q11)/Y11,"") -> 4632.8211 | AB11: =IF(OR(U11<=0,N11<=0),"Do not automate",IF(W11>R11,"Do not automate - payback exceeds process life",IF(ISNUMBER(SEARCH("AI Agent",B11)),"Consider AI agent with controls",IF(ISNUMBER(SEARCH("Coding",B11)),"Use coding copilot / structured automation",IF(ISNUMBER(SEARCH("Custom GPT",B11)),"Use Custom GPT / prompt workflow","Use manual AI / light AI"))))) -> Use coding copilot / structured automation | AC11: =IF(U11<=0,"Negative NPV: costs, review, risk, or setup exceed discounted savings.",IF(W11>R11,"Payback exceeds expected process life; wait until process stabilizes or reduce setup cost.",IF(ISNUMBER(SEARCH("AI Agent",B11)),"Agent may be justified, but only with controls, monitoring, and human approval.",IF(ISNUMBER(SEARCH("Custom GPT",B11)),"Custom GPT likely captures most value without full agent cost.","Positive NPV: use the recommended level and maintain human review.")))) -> Positive NPV: use the recommended level and maintain human review.
A12: ='1. Assumptions'!B12 -> Forecast Model Refresh | B12: ='1. Assumptions'!C12 -> AI Agent | C12: ='1. Assumptions'!D12 -> 5 | D12: =(1+'1. Assumptions'!W12)^(1/12)-1 -> 0.0079741404 | E12: ='1. Assumptions'!E12*'1. Assumptions'!F12*'1. Assumptions'!G12 -> 3520 | F12: ='1. Assumptions'!I12*'1. Assumptions'!J12 -> 0.8096 | G12: ='1. Assumptions'!E12*'1. Assumptions'!F12*'1. Assumptions'!G12*F12 -> 2849.792 | H12: =('1. Assumptions'!N12*'1. Assumptions'!P12+'1. Assumptions'!O12*'1. Assumptions'!Q12)*'1. Assumptions'!G12 -> 11.1 | I12: ='1. Assumptions'!R12 -> 1500 | J12: ='1. Assumptions'!S12*'1. Assumptions'!E12*'1. Assumptions'!G12 -> 440 | K12: ='1. Assumptions'!T12*'1. Assumptions'!U12*(1-'1. Assumptions'!V12)*'1. Assumptions'!G12 -> 120 | L12: ='1. Assumptions'!X12*'1. Assumptions'!E12 -> 1100 | M12: =H12+I12+J12+K12+L12 -> 3171.1 | N12: =G12-M12 -> -321.308 | O12: ='1. Assumptions'!K12*'1. Assumptions'!E12+'1. Assumptions'!Y12 -> 18000 | P12: ='1. Assumptions'!L12*'1. Assumptions'!M12*'1. Assumptions'!E12 -> 1760 | Q12: =O12+P12 -> 19760 | R12: ='1. Assumptions'!H12 -> 24 | S12: =IF(D12=0,R12,(1-(1+D12)^(-R12))/D12) -> 21.764568 | T12: =N12*S12 -> -6993.1297 | U12: =T12-Q12 -> -26753.13 | V12: =IF(Q12=0,"",(N12*R12-Q12)/Q12) -> -1.3902526 | W12: =IF(N12>0,Q12/N12,"") | X12: =IF((Q12+M12*R12)>0,(G12*R12)/(Q12+M12*R12),"") -> 0.71344087 | Y12: =('1. Assumptions'!N12+'1. Assumptions'!O12)*'1. Assumptions'!G12*S12 -> 36.999765 | Z12: =IF(('1. Assumptions'!N12+'1. Assumptions'!O12)*'1. Assumptions'!G12>0,H12/(('1. Assumptions'!N12+'1. Assumptions'!O12)*'1. Assumptions'!G12),"") -> 6.5294118 | AA12: =IF(Y12>0,((G12-I12-J12-K12-L12)*S12-Q12)/Y12,"") -> -716.53274 | AB12: =IF(OR(U12<=0,N12<=0),"Do not automate",IF(W12>R12,"Do not automate - payback exceeds process life",IF(ISNUMBER(SEARCH("AI Agent",B12)),"Consider AI agent with controls",IF(ISNUMBER(SEARCH("Coding",B12)),"Use coding copilot / structured automation",IF(ISNUMBER(SEARCH("Custom GPT",B12)),"Use Custom GPT / prompt workflow","Use manual AI / light AI"))))) -> Do not automate | AC12: =IF(U12<=0,"Negative NPV: costs, review, risk, or setup exceed discounted savings.",IF(W12>R12,"Payback exceeds expected process life; wait until process stabilizes or reduce setup cost.",IF(ISNUMBER(SEARCH("AI Agent",B12)),"Agent may be justified, but only with controls, monitoring, and human approval.",IF(ISNUMBER(SEARCH("Custom GPT",B12)),"Custom GPT likely captures most value without full agent cost.","Positive NPV: use the recommended level and maintain human review.")))) -> Negative NPV: costs, review, risk, or setup exceed discounted savings.
A13: ='1. Assumptions'!B13 -> Ad Hoc Business Case | B13: ='1. Assumptions'!C13 -> Manual AI | C13: ='1. Assumptions'!D13 -> 2 | D13: =(1+'1. Assumptions'!W13)^(1/12)-1 -> 0.0079741404 | E13: ='1. Assumptions'!E13*'1. Assumptions'!F13*'1. Assumptions'!G13 -> 390 | F13: ='1. Assumptions'!I13*'1. Assumptions'!J13 -> 0.41 | G13: ='1. Assumptions'!E13*'1. Assumptions'!F13*'1. Assumptions'!G13*F13 -> 159.9 | H13: =('1. Assumptions'!N13*'1. Assumptions'!P13+'1. Assumptions'!O13*'1. Assumptions'!Q13)*'1. Assumptions'!G13 -> 0.1425 | I13: ='1. Assumptions'!R13 -> 20 | J13: ='1. Assumptions'!S13*'1. Assumptions'!E13*'1. Assumptions'!G13 -> 162.5 | K13: ='1. Assumptions'!T13*'1. Assumptions'!U13*(1-'1. Assumptions'!V13)*'1. Assumptions'!G13 -> 6.75 | L13: ='1. Assumptions'!X13*'1. Assumptions'!E13 -> 26 | M13: =H13+I13+J13+K13+L13 -> 215.3925 | N13: =G13-M13 -> -55.4925 | O13: ='1. Assumptions'!K13*'1. Assumptions'!E13+'1. Assumptions'!Y13 -> 130 | P13: ='1. Assumptions'!L13*'1. Assumptions'!M13*'1. Assumptions'!E13 -> 65 | Q13: =O13+P13 -> 195 | R13: ='1. Assumptions'!H13 -> 6 | S13: =IF(D13=0,R13,(1-(1+D13)^(-R13))/D13) -> 5.836041 | T13: =N13*S13 -> -323.85651 | U13: =T13-Q13 -> -518.85651 | V13: =IF(Q13=0,"",(N13*R13-Q13)/Q13) -> -2.7074615 | W13: =IF(N13>0,Q13/N13,"") | X13: =IF((Q13+M13*R13)>0,(G13*R13)/(Q13+M13*R13),"") -> 0.64503767 | Y13: =('1. Assumptions'!N13+'1. Assumptions'!O13)*'1. Assumptions'!G13*S13 -> 0.10213072 | Z13: =IF(('1. Assumptions'!N13+'1. Assumptions'!O13)*'1. Assumptions'!G13>0,H13/(('1. Assumptions'!N13+'1. Assumptions'!O13)*'1. Assumptions'!G13),"") -> 8.1428571 | AA13: =IF(Y13>0,((G13-I13-J13-K13-L13)*S13-Q13)/Y13,"") -> -5072.175 | AB13: =IF(OR(U13<=0,N13<=0),"Do not automate",IF(W13>R13,"Do not automate - payback exceeds process life",IF(ISNUMBER(SEARCH("AI Agent",B13)),"Consider AI agent with controls",IF(ISNUMBER(SEARCH("Coding",B13)),"Use coding copilot / structured automation",IF(ISNUMBER(SEARCH("Custom GPT",B13)),"Use Custom GPT / prompt workflow","Use manual AI / light AI"))))) -> Do not automate | AC13: =IF(U13<=0,"Negative NPV: costs, review, risk, or setup exceed discounted savings.",IF(W13>R13,"Payback exceeds expected process life; wait until process stabilizes or reduce setup cost.",IF(ISNUMBER(SEARCH("AI Agent",B13)),"Agent may be justified, but only with controls, monitoring, and human approval.",IF(ISNUMBER(SEARCH("Custom GPT",B13)),"Custom GPT likely captures most value without full agent cost.","Positive NPV: use the recommended level and maintain human review.")))) -> Negative NPV: costs, review, risk, or setup exceed discounted savings.
A14: ='1. Assumptions'!B14 -> Ad Hoc Business Case | B14: ='1. Assumptions'!C14 -> Custom GPT | C14: ='1. Assumptions'!D14 -> 3 | D14: =(1+'1. Assumptions'!W14)^(1/12)-1 -> 0.0079741404 | E14: ='1. Assumptions'!E14*'1. Assumptions'!F14*'1. Assumptions'!G14 -> 390 | F14: ='1. Assumptions'!I14*'1. Assumptions'!J14 -> 0.595 | G14: ='1. Assumptions'!E14*'1. Assumptions'!F14*'1. Assumptions'!G14*F14 -> 232.05 | H14: =('1. Assumptions'!N14*'1. Assumptions'!P14+'1. Assumptions'!O14*'1. Assumptions'!Q14)*'1. Assumptions'!G14 -> 0.3 | I14: ='1. Assumptions'!R14 -> 50 | J14: ='1. Assumptions'!S14*'1. Assumptions'!E14*'1. Assumptions'!G14 -> 130 | K14: ='1. Assumptions'!T14*'1. Assumptions'!U14*(1-'1. Assumptions'!V14)*'1. Assumptions'!G14 -> 5.625 | L14: ='1. Assumptions'!X14*'1. Assumptions'!E14 -> 104 | M14: =H14+I14+J14+K14+L14 -> 289.925 | N14: =G14-M14 -> -57.875 | O14: ='1. Assumptions'!K14*'1. Assumptions'!E14+'1. Assumptions'!Y14 -> 1040 | P14: ='1. Assumptions'!L14*'1. Assumptions'!M14*'1. Assumptions'!E14 -> 520 | Q14: =O14+P14 -> 1560 | R14: ='1. Assumptions'!H14 -> 6 | S14: =IF(D14=0,R14,(1-(1+D14)^(-R14))/D14) -> 5.836041 | T14: =N14*S14 -> -337.76087 | U14: =T14-Q14 -> -1897.7609 | V14: =IF(Q14=0,"",(N14*R14-Q14)/Q14) -> -1.2225962 | W14: =IF(N14>0,Q14/N14,"") | X14: =IF((Q14+M14*R14)>0,(G14*R14)/(Q14+M14*R14),"") -> 0.42196663 | Y14: =('1. Assumptions'!N14+'1. Assumptions'!O14)*'1. Assumptions'!G14*S14 -> 0.23344164 | Z14: =IF(('1. Assumptions'!N14+'1. Assumptions'!O14)*'1. Assumptions'!G14>0,H14/(('1. Assumptions'!N14+'1. Assumptions'!O14)*'1. Assumptions'!G14),"") -> 7.5 | AA14: =IF(Y14>0,((G14-I14-J14-K14-L14)*S14-Q14)/Y14,"") -> -8121.9874 | AB14: =IF(OR(U14<=0,N14<=0),"Do not automate",IF(W14>R14,"Do not automate - payback exceeds process life",IF(ISNUMBER(SEARCH("AI Agent",B14)),"Consider AI agent with controls",IF(ISNUMBER(SEARCH("Coding",B14)),"Use coding copilot / structured automation",IF(ISNUMBER(SEARCH("Custom GPT",B14)),"Use Custom GPT / prompt workflow","Use manual AI / light AI"))))) -> Do not automate | AC14: =IF(U14<=0,"Negative NPV: costs, review, risk, or setup exceed discounted savings.",IF(W14>R14,"Payback exceeds expected process life; wait until process stabilizes or reduce setup cost.",IF(ISNUMBER(SEARCH("AI Agent",B14)),"Agent may be justified, but only with controls, monitoring, and human approval.",IF(ISNUMBER(SEARCH("Custom GPT",B14)),"Custom GPT likely captures most value without full agent cost.","Positive NPV: use the recommended level and maintain human review.")))) -> Negative NPV: costs, review, risk, or setup exceed discounted savings.
A15: ='1. Assumptions'!B15 -> ERP Forecast Upload | B15: ='1. Assumptions'!C15 -> Coding Copilot | C15: ='1. Assumptions'!D15 -> 4 | D15: =(1+'1. Assumptions'!W15)^(1/12)-1 -> 0.0079741404 | E15: ='1. Assumptions'!E15*'1. Assumptions'!F15*'1. Assumptions'!G15 -> 1260 | F15: ='1. Assumptions'!I15*'1. Assumptions'!J15 -> 0.585 | G15: ='1. Assumptions'!E15*'1. Assumptions'!F15*'1. Assumptions'!G15*F15 -> 737.1 | H15: =('1. Assumptions'!N15*'1. Assumptions'!P15+'1. Assumptions'!O15*'1. Assumptions'!Q15)*'1. Assumptions'!G15 -> 0.75 | I15: ='1. Assumptions'!R15 -> 150 | J15: ='1. Assumptions'!S15*'1. Assumptions'!E15*'1. Assumptions'!G15 -> 315 | K15: ='1. Assumptions'!T15*'1. Assumptions'!U15*(1-'1. Assumptions'!V15)*'1. Assumptions'!G15 -> 90 | L15: ='1. Assumptions'!X15*'1. Assumptions'!E15 -> 210 | M15: =H15+I15+J15+K15+L15 -> 765.75 | N15: =G15-M15 -> -28.65 | O15: ='1. Assumptions'!K15*'1. Assumptions'!E15+'1. Assumptions'!Y15 -> 3520 | P15: ='1. Assumptions'!L15*'1. Assumptions'!M15*'1. Assumptions'!E15 -> 630 | Q15: =O15+P15 -> 4150 | R15: ='1. Assumptions'!H15 -> 18 | S15: =IF(D15=0,R15,(1-(1+D15)^(-R15))/D15) -> 16.70598 | T15: =N15*S15 -> -478.62632 | U15: =T15-Q15 -> -4628.6263 | V15: =IF(Q15=0,"",(N15*R15-Q15)/Q15) -> -1.1242651 | W15: =IF(N15>0,Q15/N15,"") | X15: =IF((Q15+M15*R15)>0,(G15*R15)/(Q15+M15*R15),"") -> 0.73983327 | Y15: =('1. Assumptions'!N15+'1. Assumptions'!O15)*'1. Assumptions'!G15*S15 -> 2.1717774 | Z15: =IF(('1. Assumptions'!N15+'1. Assumptions'!O15)*'1. Assumptions'!G15>0,H15/(('1. Assumptions'!N15+'1. Assumptions'!O15)*'1. Assumptions'!G15),"") -> 5.7692308 | AA15: =IF(Y15>0,((G15-I15-J15-K15-L15)*S15-Q15)/Y15,"") -> -2125.4927 | AB15: =IF(OR(U15<=0,N15<=0),"Do not automate",IF(W15>R15,"Do not automate - payback exceeds process life",IF(ISNUMBER(SEARCH("AI Agent",B15)),"Consider AI agent with controls",IF(ISNUMBER(SEARCH("Coding",B15)),"Use coding copilot / structured automation",IF(ISNUMBER(SEARCH("Custom GPT",B15)),"Use Custom GPT / prompt workflow","Use manual AI / light AI"))))) -> Do not automate | AC15: =IF(U15<=0,"Negative NPV: costs, review, risk, or setup exceed discounted savings.",IF(W15>R15,"Payback exceeds expected process life; wait until process stabilizes or reduce setup cost.",IF(ISNUMBER(SEARCH("AI Agent",B15)),"Agent may be justified, but only with controls, monitoring, and human approval.",IF(ISNUMBER(SEARCH("Custom GPT",B15)),"Custom GPT likely captures most value without full agent cost.","Positive NPV: use the recommended level and maintain human review.")))) -> Negative NPV: costs, review, risk, or setup exceed discounted savings.
A16: ='1. Assumptions'!B16 -> ERP Forecast Upload | B16: ='1. Assumptions'!C16 -> AI Agent | C16: ='1. Assumptions'!D16 -> 5 | D16: =(1+'1. Assumptions'!W16)^(1/12)-1 -> 0.0079741404 | E16: ='1. Assumptions'!E16*'1. Assumptions'!F16*'1. Assumptions'!G16 -> 1260 | F16: ='1. Assumptions'!I16*'1. Assumptions'!J16 -> 0.7998 | G16: ='1. Assumptions'!E16*'1. Assumptions'!F16*'1. Assumptions'!G16*F16 -> 1007.748 | H16: =('1. Assumptions'!N16*'1. Assumptions'!P16+'1. Assumptions'!O16*'1. Assumptions'!Q16)*'1. Assumptions'!G16 -> 6.9 | I16: ='1. Assumptions'!R16 -> 1800 | J16: ='1. Assumptions'!S16*'1. Assumptions'!E16*'1. Assumptions'!G16 -> 210 | K16: ='1. Assumptions'!T16*'1. Assumptions'!U16*(1-'1. Assumptions'!V16)*'1. Assumptions'!G16 -> 160 | L16: ='1. Assumptions'!X16*'1. Assumptions'!E16 -> 1260 | M16: =H16+I16+J16+K16+L16 -> 3436.9 | N16: =G16-M16 -> -2429.152 | O16: ='1. Assumptions'!K16*'1. Assumptions'!E16+'1. Assumptions'!Y16 -> 22600 | P16: ='1. Assumptions'!L16*'1. Assumptions'!M16*'1. Assumptions'!E16 -> 1680 | Q16: =O16+P16 -> 24280 | R16: ='1. Assumptions'!H16 -> 18 | S16: =IF(D16=0,R16,(1-(1+D16)^(-R16))/D16) -> 16.70598 | T16: =N16*S16 -> -40581.364 | U16: =T16-Q16 -> -64861.364 | V16: =IF(Q16=0,"",(N16*R16-Q16)/Q16) -> -2.800854 | W16: =IF(N16>0,Q16/N16,"") | X16: =IF((Q16+M16*R16)>0,(G16*R16)/(Q16+M16*R16),"") -> 0.21057093 | Y16: =('1. Assumptions'!N16+'1. Assumptions'!O16)*'1. Assumptions'!G16*S16 -> 18.376578 | Z16: =IF(('1. Assumptions'!N16+'1. Assumptions'!O16)*'1. Assumptions'!G16>0,H16/(('1. Assumptions'!N16+'1. Assumptions'!O16)*'1. Assumptions'!G16),"") -> 6.2727273 | AA16: =IF(Y16>0,((G16-I16-J16-K16-L16)*S16-Q16)/Y16,"") -> -3523.2944 | AB16: =IF(OR(U16<=0,N16<=0),"Do not automate",IF(W16>R16,"Do not automate - payback exceeds process life",IF(ISNUMBER(SEARCH("AI Agent",B16)),"Consider AI agent with controls",IF(ISNUMBER(SEARCH("Coding",B16)),"Use coding copilot / structured automation",IF(ISNUMBER(SEARCH("Custom GPT",B16)),"Use Custom GPT / prompt workflow","Use manual AI / light AI"))))) -> Do not automate | AC16: =IF(U16<=0,"Negative NPV: costs, review, risk, or setup exceed discounted savings.",IF(W16>R16,"Payback exceeds expected process life; wait until process stabilizes or reduce setup cost.",IF(ISNUMBER(SEARCH("AI Agent",B16)),"Agent may be justified, but only with controls, monitoring, and human approval.",IF(ISNUMBER(SEARCH("Custom GPT",B16)),"Custom GPT likely captures most value without full agent cost.","Positive NPV: use the recommended level and maintain human review.")))) -> Negative NPV: costs, review, risk, or setup exceed discounted savings.

Sheet 3. Dashboard
A1: Dashboard — Best AI option by FP&A process
A2: Decision rule: maximize NPV, but only automate when NPV is positive and payback is shorter than expected process life.
A4: Total Positive NPV | B4: Positive AI Cases | D4: Avg. Payback (positive cases) | E4: Best Overall Case
A5: =SUMIF('2. Calculations'!U5:U16,">0",'2. Calculations'!U5:U16) -> 25087.646 | B5: =COUNTIF('2. Calculations'!U5:U16,">0") -> 2 | D5: =AVERAGEIF('2. Calculations'!U5:U16,">0",'2. Calculations'!W5:W16) -> 4.1309332 | E5: =INDEX('2. Calculations'!A5:A16,MATCH(MAX('2. Calculations'!U5:U16),'2. Calculations'!U5:U16,0))&" — "&INDEX('2. Calculations'!B5:B16,MATCH(MAX('2. Calculations'!U5:U16),'2. Calculations'!U5:U16,0)) -> Forecast Model Refresh — Coding Copilot
A8: Process | B8: Recommended Option | C8: Best NPV | D8: Monthly Net Savings | E8: Payback Months | F8: AI Score | G8: Token Break-even ($/1M) | H8: CFO Action
A9: Monthly Variance Analysis
A10: Board Deck Commentary
A11: Forecast Model Refresh
A12: Ad Hoc Business Case
A13: ERP Forecast Upload
A16: CFO Interpretation
A17: Use the recommendation only if the business process is stable enough to earn back setup and learning costs. If token prices keep falling, AI agents may become viable later; use the Token Breakeven sheet to calculate the price point. Even when an agent passes the model, keep human review for financial outputs because accountability does not get automated.

Sheet Bonus Token Breakeven
A1: Token Breakeven — When would an AI agent become economically justified?
A2: This sheet solves the price point at which token costs are low enough for each option to pass the CFO model. It also compares AI Agent vs Custom GPT for selected processes.
A4: Standalone break-even token price by option
A5: Process | B5: AI Option | C5: NPV | D5: Actual Blended Token Price ($/1M) | E5: Max Break-even Token Price ($/1M) | F5: Token Price Headroom | G5: Payback Months | H5: Recommendation | I5: CFO Interpretation
A6: ='2. Calculations'!A5 -> Monthly Variance Analysis | B6: ='2. Calculations'!B5 -> Manual AI | C6: ='2. Calculations'!U5 -> -2116.1071 | D6: ='2. Calculations'!Z5 -> 7 | E6: ='2. Calculations'!AA5 -> -4215.2547 | F6: =E6-D6 -> -4222.2547 | G6: ='2. Calculations'!W5 | H6: ='2. Calculations'!AB5 -> Do not automate | I6: =IF(C6<=0,"Not viable today. Revisit if token/tool costs fall or setup is reduced.",IF(D6<E6,"Token price is below break-even. Check controls and human review.","Token price is above break-even. Agent/tool is too expensive at current assumptions.")) -> Not viable today. Revisit if token/tool costs fall or setup is reduced.
A7: ='2. Calculations'!A6 -> Monthly Variance Analysis | B7: ='2. Calculations'!B6 -> Custom GPT | C7: ='2. Calculations'!U6 -> 2934.7841 | D7: ='2. Calculations'!Z6 -> 7 | E7: ='2. Calculations'!AA6 -> 2349.3023 | F7: =E7-D7 -> 2342.3023 | G7: ='2. Calculations'!W6 -> 5.3955102 | H7: ='2. Calculations'!AB6 -> Use Custom GPT / prompt workflow | I7: =IF(C7<=0,"Not viable today. Revisit if token/tool costs fall or setup is reduced.",IF(D7<E7,"Token price is below break-even. Check controls and human review.","Token price is above break-even. Agent/tool is too expensive at current assumptions.")) -> Token price is below break-even. Check controls and human review.
A8: ='2. Calculations'!A7 -> Monthly Variance Analysis | B8: ='2. Calculations'!B7 -> AI Agent | C8: ='2. Calculations'!U7 -> -32460.726 | D8: ='2. Calculations'!Z7 -> 7 | E8: ='2. Calculations'!AA7 -> -4310.9118 | F8: =E8-D8 -> -4317.9118 | G8: ='2. Calculations'!W7 | H8: ='2. Calculations'!AB7 -> Do not automate | I8: =IF(C8<=0,"Not viable today. Revisit if token/tool costs fall or setup is reduced.",IF(D8<E8,"Token price is below break-even. Check controls and human review.","Token price is above break-even. Agent/tool is too expensive at current assumptions.")) -> Not viable today. Revisit if token/tool costs fall or setup is reduced.
A9: ='2. Calculations'!A8 -> Board Deck Commentary | B9: ='2. Calculations'!B8 -> Manual AI | C9: ='2. Calculations'!U8 -> -3236.2291 | D9: ='2. Calculations'!Z8 -> 7.8 | E9: ='2. Calculations'!AA8 -> -5669.5519 | F9: =E9-D9 -> -5677.3519 | G9: ='2. Calculations'!W8 | H9: ='2. Calculations'!AB8 -> Do not automate | I9: =IF(C9<=0,"Not viable today. Revisit if token/tool costs fall or setup is reduced.",IF(D9<E9,"Token price is below break-even. Check controls and human review.","Token price is above break-even. Agent/tool is too expensive at current assumptions.")) -> Not viable today. Revisit if token/tool costs fall or setup is reduced.
A10: ='2. Calculations'!A9 -> Board Deck Commentary | B10: ='2. Calculations'!B9 -> Custom GPT | C10: ='2. Calculations'!U9 -> -1715.2078 | D10: ='2. Calculations'!Z9 -> 7.8 | E10: ='2. Calculations'!AA9 -> -1496.7038 | F10: =E10-D10 -> -1504.5038 | G10: ='2. Calculations'!W9 | H10: ='2. Calculations'!AB9 -> Do not automate | I10: =IF(C10<=0,"Not viable today. Revisit if token/tool costs fall or setup is reduced.",IF(D10<E10,"Token price is below break-even. Check controls and human review.","Token price is above break-even. Agent/tool is too expensive at current assumptions.")) -> Not viable today. Revisit if token/tool costs fall or setup is reduced.
A11: ='2. Calculations'!A10 -> Board Deck Commentary | B11: ='2. Calculations'!B10 -> AI Agent | C11: ='2. Calculations'!U10 -> -29126.317 | D11: ='2. Calculations'!Z10 -> 8.3333333 | E11: ='2. Calculations'!AA10 -> -5669.0683 | F11: =E11-D11 -> -5677.4016 | G11: ='2. Calculations'!W10 | H11: ='2. Calculations'!AB10 -> Do not automate | I11: =IF(C11<=0,"Not viable today. Revisit if token/tool costs fall or setup is reduced.",IF(D11<E11,"Token price is below break-even. Check controls and human review.","Token price is above break-even. Agent/tool is too expensive at current assumptions.")) -> Not viable today. Revisit if token/tool costs fall or setup is reduced.
A12: ='2. Calculations'!A11 -> Forecast Model Refresh | B12: ='2. Calculations'!B11 -> Coding Copilot | C12: ='2. Calculations'!U11 -> 22152.862 | D12: ='2. Calculations'!Z11 -> 6.2727273 | E12: ='2. Calculations'!AA11 -> 4632.8211 | F12: =E12-D12 -> 4626.5484 | G12: ='2. Calculations'!W11 -> 2.8663561 | H12: ='2. Calculations'!AB11 -> Use coding copilot / structured automation | I12: =IF(C12<=0,"Not viable today. Revisit if token/tool costs fall or setup is reduced.",IF(D12<E12,"Token price is below break-even. Check controls and human review.","Token price is above break-even. Agent/tool is too expensive at current assumptions.")) -> Token price is below break-even. Check controls and human review.
A13: ='2. Calculations'!A12 -> Forecast Model Refresh | B13: ='2. Calculations'!B12 -> AI Agent | C13: ='2. Calculations'!U12 -> -26753.13 | D13: ='2. Calculations'!Z12 -> 6.5294118 | E13: ='2. Calculations'!AA12 -> -716.53274 | F13: =E13-D13 -> -723.06215 | G13: ='2. Calculations'!W12 | H13: ='2. Calculations'!AB12 -> Do not automate | I13: =IF(C13<=0,"Not viable today. Revisit if token/tool costs fall or setup is reduced.",IF(D13<E13,"Token price is below break-even. Check controls and human review.","Token price is above break-even. Agent/tool is too expensive at current assumptions.")) -> Not viable today. Revisit if token/tool costs fall or setup is reduced.
A14: ='2. Calculations'!A13 -> Ad Hoc Business Case | B14: ='2. Calculations'!B13 -> Manual AI | C14: ='2. Calculations'!U13 -> -518.85651 | D14: ='2. Calculations'!Z13 -> 8.1428571 | E14: ='2. Calculations'!AA13 -> -5072.175 | F14: =E14-D14 -> -5080.3178 | G14: ='2. Calculations'!W13 | H14: ='2. Calculations'!AB13 -> Do not automate | I14: =IF(C14<=0,"Not viable today. Revisit if token/tool costs fall or setup is reduced.",IF(D14<E14,"Token price is below break-even. Check controls and human review.","Token price is above break-even. Agent/tool is too expensive at current assumptions.")) -> Not viable today. Revisit if token/tool costs fall or setup is reduced.
A15: ='2. Calculations'!A14 -> Ad Hoc Business Case | B15: ='2. Calculations'!B14 -> Custom GPT | C15: ='2. Calculations'!U14 -> -1897.7609 | D15: ='2. Calculations'!Z14 -> 7.5 | E15: ='2. Calculations'!AA14 -> -8121.9874 | F15: =E15-D15 -> -8129.4874 | G15: ='2. Calculations'!W14 | H15: ='2. Calculations'!AB14 -> Do not automate | I15: =IF(C15<=0,"Not viable today. Revisit if token/tool costs fall or setup is reduced.",IF(D15<E15,"Token price is below break-even. Check controls and human review.","Token price is above break-even. Agent/tool is too expensive at current assumptions.")) -> Not viable today. Revisit if token/tool costs fall or setup is reduced.
A16: ='2. Calculations'!A15 -> ERP Forecast Upload | B16: ='2. Calculations'!B15 -> Coding Copilot | C16: ='2. Calculations'!U15 -> -4628.6263 | D16: ='2. Calculations'!Z15 -> 5.7692308 | E16: ='2. Calculations'!AA15 -> -2125.4927 | F16: =E16-D16 -> -2131.2619 | G16: ='2. Calculations'!W15 | H16: ='2. Calculations'!AB15 -> Do not automate | I16: =IF(C16<=0,"Not viable today. Revisit if token/tool costs fall or setup is reduced.",IF(D16<E16,"Token price is below break-even. Check controls and human review.","Token price is above break-even. Agent/tool is too expensive at current assumptions.")) -> Not viable today. Revisit if token/tool costs fall or setup is reduced.
A17: ='2. Calculations'!A16 -> ERP Forecast Upload | B17: ='2. Calculations'!B16 -> AI Agent | C17: ='2. Calculations'!U16 -> -64861.364 | D17: ='2. Calculations'!Z16 -> 6.2727273 | E17: ='2. Calculations'!AA16 -> -3523.2944 | F17: =E17-D17 -> -3529.5671 | G17: ='2. Calculations'!W16 | H17: ='2. Calculations'!AB16 -> Do not automate | I17: =IF(C17<=0,"Not viable today. Revisit if token/tool costs fall or setup is reduced.",IF(D17<E17,"Token price is below break-even. Check controls and human review.","Token price is above break-even. Agent/tool is too expensive at current assumptions.")) -> Not viable today. Revisit if token/tool costs fall or setup is reduced.
A20: Incremental comparison: AI Agent vs Custom GPT
A21: Process | B21: Custom GPT Calc Row | C21: Agent Calc Row | D21: Extra Monthly Value Excl. Tokens | E21: Extra Upfront Cost | F21: Extra PV Tokens Used (M) | G21: Incremental Break-even Token Price ($/1M) | H21: Actual Agent Token Price ($/1M) | I21: Decision
A22: Monthly Variance Analysis | B22: 6 | C22: 7 | D22: =('2. Calculations'!G7-'2. Calculations'!I7-'2. Calculations'!J7-'2. Calculations'!K7-'2. Calculations'!L7)-('2. Calculations'!G6-'2. Calculations'!I6-'2. Calculations'!J6-'2. Calculations'!K6-'2. Calculations'!L6) -> -1314 | E22: ='2. Calculations'!Q7-'2. Calculations'!Q6 -> 13400 | F22: ='2. Calculations'!Y7-'2. Calculations'!Y6 -> 6.2647424 | G22: =IF(F22>0,(D22*'2. Calculations'!S7-E22)/F22,"") -> -5642.9547 | H22: ='2. Calculations'!Z7 -> 7 | I22: =IF(G22<=0,"Agent not justified at any positive token price under these assumptions",IF(H22<G22,"Agent could beat Custom GPT if controls are acceptable","Custom GPT still better until tokens/tooling get cheaper or setup falls")) -> Agent not justified at any positive token price under these assumptions
A23: Board Deck Commentary | B23: 9 | C23: 10 | D23: =('2. Calculations'!G10-'2. Calculations'!I10-'2. Calculations'!J10-'2. Calculations'!K10-'2. Calculations'!L10)-('2. Calculations'!G9-'2. Calculations'!I9-'2. Calculations'!J9-'2. Calculations'!K9-'2. Calculations'!L9) -> -1282.16 | E23: ='2. Calculations'!Q10-'2. Calculations'!Q9 -> 12760 | F23: ='2. Calculations'!Y10-'2. Calculations'!Y9 -> 3.9901707 | G23: =IF(F23>0,(D23*'2. Calculations'!S10-E23)/F23,"") -> -6861.1724 | H23: ='2. Calculations'!Z10 -> 8.3333333 | I23: =IF(G23<=0,"Agent not justified at any positive token price under these assumptions",IF(H23<G23,"Agent could beat Custom GPT if controls are acceptable","Custom GPT still better until tokens/tooling get cheaper or setup falls")) -> Agent not justified at any positive token price under these assumptions
A26: CFO note: Cheaper tokens can move the break-even point, but they do not eliminate setup, integration, monitoring, risk, or human review. The future agent may become cheap to run, but still expensive to trust.

Sheet Bonus Python
B2: I also created a Python code that can calculate this.
B4: It's free for you to use:
B6: https://colab.research.google.com/drive/1HcgyKElPZNzBr9w_Y2Fs1y01cuaDuVk2?usp=sharing
